aporthq_sdk_python/__init__.py
aporthq_sdk_python/client.py
aporthq_sdk_python/decision_types.py
aporthq_sdk_python/errors.py
aporthq_sdk_python/exceptions.py
aporthq_sdk_python/shared_types.py
aporthq_sdk_python-0.1.1.dist-info/licenses/LICENSE
aporthq_sdk_python-0.1.1.dist-info/METADATA
aporthq_sdk_python-0.1.1.dist-info/WHEEL
aporthq_sdk_python-0.1.1.dist-info/top_level.txt
aporthq_sdk_python-0.1.1.dist-info/RECORD
