Metadata-Version: 2.4
Name: aporthq-sdk-python
Version: 0.1.1
Summary: Python SDK for The Passport for AI Agents
Author-email: APort Team <team@aport.io>
License: MIT
Project-URL: Homepage, https://aport.io
Project-URL: Documentation, https://aport.io/docs
Project-URL: Repository, https://github.com/aporthq/aport-sdks-and-middlewares
Project-URL: Issues, https://github.com/aporthq/aport-sdks-and-middlewares/issues
Keywords: agent-passport,ai,authentication,verification,aport,mcp,middleware
Classifier: Development Status :: 4 - Beta
Classifier: Intended Audience :: Developers
Classifier: Programming Language :: Python :: 3
Classifier: Programming Language :: Python :: 3.8
Classifier: Programming Language :: Python :: 3.9
Classifier: Programming Language :: Python :: 3.10
Classifier: Programming Language :: Python :: 3.11
Classifier: Programming Language :: Python :: 3.12
Classifier: Topic :: Software Development :: Libraries :: Python Modules
Classifier: Topic :: Security
Classifier: Topic :: Internet :: WWW/HTTP :: Dynamic Content
Requires-Python: >=3.8
License-File: LICENSE
Requires-Dist: aiohttp>=3.8.0
Requires-Dist: typing-extensions>=4.0.0
Provides-Extra: dev
Requires-Dist: pytest>=7.0.0; extra == "dev"
Requires-Dist: pytest-cov>=4.0.0; extra == "dev"
Requires-Dist: black>=22.0.0; extra == "dev"
Requires-Dist: isort>=5.0.0; extra == "dev"
Requires-Dist: mypy>=1.0.0; extra == "dev"
Dynamic: license-file
